hacs_api/__init__.py
hacs_api/auth.py
hacs_api/main.py
hacs_api/py.typed
hacs_api-0.2.2.dist-info/METADATA
hacs_api-0.2.2.dist-info/WHEEL
hacs_api-0.2.2.dist-info/entry_points.txt
hacs_api-0.2.2.dist-info/RECORD
